guided_lambda_handler/__init__.py
guided_lambda_handler/guided_lambda_handler.py
guided_lambda_handler/translators.py
guided_lambda_handler_tj-0.0.24.dist-info/METADATA
guided_lambda_handler_tj-0.0.24.dist-info/WHEEL
guided_lambda_handler_tj-0.0.24.dist-info/top_level.txt
guided_lambda_handler_tj-0.0.24.dist-info/RECORD
