Metadata-Version: 2.1
Name: guided-lambda-handler-tj
Version: 0.0.24
Summary: lambda handling framework
Home-page: https://github.com/tbindseil/sts-mono-repo
Author: tj
Author-email: tjbindseil@gmail.com
License: UNKNOWN
Platform: UNKNOWN
Classifier: Programming Language :: Python :: 3
Classifier: License :: OSI Approved :: MIT License
Classifier: Operating System :: OS Independent
Requires-Python: >=3.6
Requires-Dist: sts-validate-authentication-aws-cognito-tj
Requires-Dist: sts-json-datetime (>=0.0.9)
Requires-Dist: sts-db-utils-tj
